[
  {
    "url": "/gph/app/wateropen/getWaterOpenList",
    "method": "post",
    "response": {
      "code": "0",
      "message": "",
      "body": [
        {
          "letter": "D",
          "rivers": [
            {
              "time": "2017-11-12",
              "position": "大良街道",
              "name": "福田涌",
              "index": "D"
            }
          ]
        },
        {
          "letter": "S",
          "rivers": [
            {
              "time": "2017-11-12",
              "position": "大良街道",
              "name": "石排涌",
              "index": "S"
            },
            {
              "time": "2017-11-12",
              "position": "大良街道",
              "name": "石排涌2",
              "index": "S"
            },
            {
              "time": "2017-11-12",
              "position": "大良街道",
              "name": "石排涌3",
              "index": "S"
            }
          ]
        },
        {
          "letter": "L",
          "rivers": [
            {
              "time": "2017-11-12",
              "position": "大良街道",
              "name": "龙公涌",
              "index": "L"
            },
            {
              "time": "2017-11-12",
              "position": "大良街道",
              "name": "龙公涌2",
              "index": "L"
            },
            {
              "time": "2017-11-12",
              "position": "大良街道",
              "name": "龙公涌3",
              "index": "L"
            },
            {
              "time": "2017-11-12",
              "position": "大良街道",
              "name": "龙公涌4",
              "index": "L"
            }
          ]
        },
        {
          "letter": "G",
          "rivers": [
            {
              "time": "2017-11-12",
              "position": "大良街道",
              "name": "古鉴涌",
              "index": "G"
            }
          ]
        },
        {
          "letter": "H",
          "rivers": [
            {
              "time": "2017-11-12",
              "position": "大良街道",
              "name": "合耕围涌",
              "index": "H"
            }
          ]
        },
        {
          "letter": "Y",
          "rivers": [
            {
              "time": "2017-11-12",
              "position": "大良街道",
              "name": "云路初街涌",
              "index": "Y"
            }
          ]
        },
        {
          "letter": "P",
          "rivers": [
            {
              "time": "2017-11-12",
              "position": "大良街道",
              "name": "排涌",
              "index": "P"
            }
          ]
        }
      ]
    }
  },
  {
    "url": "/gph/app/wateropen/getWaterOpenDetail",
    "method": "post",
    "response": {
      "code": "0",
      "message": "",
      "body": {
        "basic": {
          "name": "福田涌",
          "location": "大良街道",
          "atWater": "福田涌",
          "waterType": "IV",
          "source": "顺德区环境运输和城市管理局"
        },
        "echart": {
          "DO": [
            3.72,
            5.12,
            5.72,
            6.73,
            7.72,
            5.52
          ],
          "CDO": [
            3.72,
            5.12,
            5.72,
            6.73,
            7.72,
            5.52
          ],
          "NH3-N": [
            3.72,
            5.12,
            5.72,
            6.73,
            7.72,
            5.52
          ],
          "TP": [
            3.72,
            5.12,
            5.72,
            6.73,
            7.72,
            5.52
          ]
        }
      }
    }
  },
  {
    "url": "/gph/app/raindistibution/getRainDistributionList",
    "method": "post",
    "response": {
      "code": "0",
      "message": "",
      "body": [
        {
          "letter": "L",
          "rains": [
            {
              "starttime": "2017-09-21 8:00",
              "temperature": "15",
              "position": "伦教街道",
              "rainsize": "19.1mm",
              "name": "伦教中学",
              "variety": 1
            },
            {
              "starttime": "2017-09-21 8:00",
              "temperature": "13",
              "position": "伦教街道",
              "rainsize": "20mm",
              "name": "伦教良仁涌水闸",
              "variety": 2
            },
            {
              "starttime": "2017-09-21 8:00",
              "temperature": "12",
              "position": "大良",
              "rainsize": "23mm",
              "name": "顺德区政府",
              "variety": 3
            }
          ]
        },
        {
          "letter": "D",
          "rains": [
            {
              "starttime": "2017-09-21 8:00",
              "temperature": "19",
              "position": "大良街道",
              "rainsize": "21mm",
              "name": "大良顺德港",
              "variety": 1
            },
            {
              "starttime": "2017-09-21 8:00",
              "temperature": "21",
              "position": "大良街道",
              "rainsize": "22mm",
              "name": "大良一中附小",
              "variety": 3
            },
            {
              "starttime": "2017-09-21 8:00",
              "temperature": "22",
              "position": "大良街道",
              "rainsize": "21mm",
              "name": "大良沙头水闸",
              "variety": 4
            }
          ]
        },
        {
          "letter": "S",
          "rains": [
            {
              "starttime": "2017-09-21 8:00",
              "temperature": "23",
              "position": "大良街道",
              "rainsize": "23mm",
              "name": "顺峰山公园生态站",
              "variety": 4
            }
          ]
        },
        {
          "letter": "F",
          "rains": [
            {
              "starttime": "2017-09-21 8:00",
              "temperature": "25",
              "position": "大良街道",
              "rainsize": "22mm",
              "name": "逢沙电排站",
              "variety": 2
            }
          ]
        }
      ]
    }
  },
  {
    "url": "/gph/app/raindistibution/getRainDistributionDetail",
    "method": "post",
    "response": {
      "code": "0",
      "message": "",
      "body": {
        "location": "伦教街道",
        "dataSource": "顺德区气象局",
        "rainAll": {
          "size": "0.8mm",
          "temperature": "22",
          "startTime": "2017-11-23 1:00",
          "endTime": "2017-11-24 11:00"
        },
        "rainHigh": {
          "size": "0.2mm",
          "time": "2017-11-23 1:00"
        },
        "rainLow": {
          "size": "0mm",
          "time": "2017-11-23 21:00"
        }
      }
    }
  },
  {
    "url": "/gph/app/riverchief/getRiverChiefList",
    "method": "post",
    "response": {
      "code": "0",
      "message": "",
      "body": [
        {
          "letter": "G",
          "rivers": [
            {
              "river": "桂畔海河",
              "level": "区级河长",
              "warden": "黄海",
              "length": "13500",
              "start": "桂畔海水利枢纽",
              "end": "新滘节制闸"
            }
          ]
        },
        {
          "letter": "D",
          "rivers": [
            {
              "river": "大良河",
              "level": "区级河长",
              "warden": "黄海",
              "length": "13500",
              "start": "金桔咀桥",
              "end": "新滘四河口"
            },
            {
              "river": "大门河",
              "level": "区级河长",
              "warden": "黄海",
              "length": "13500",
              "start": "大门滘船闸",
              "end": "金桔咀桥"
            }
          ]
        },
        {
          "letter": "L",
          "rivers": [
            {
              "river": "龙工涌",
              "level": "区级河长",
              "warden": "黄海",
              "length": "13500",
              "start": "合成涵闸",
              "end": "大东人工河"
            }
          ]
        },
        {
          "letter": "Y",
          "rivers": [
            {
              "river": "银涌河",
              "level": "区级河长",
              "warden": "吴显强",
              "length": "13500",
              "start": "桂畔海逢沙三眼桥",
              "end": "金桔咀桥"
            }
          ]
        }
      ]
    }
  },
  {
    "url": "/gph/app/riverchief/getRiverChiefDetail",
    "method": "post",
    "response": {
      "code": "0",
      "message": "",
      "body": {
        "riverChiefDetail": [
          {
            "level": "区级河长",
            "name": "黄海",
            "tab": "顺德区区长"
          },
          {
            "level": "镇级河长",
            "name": "吴显强",
            "tab": "大良街道办主任"
          },
          {
            "level": "村级河长",
            "name": "高锡洪",
            "tab": "新滘居委会书记"
          },
          {
            "level": "村级河长",
            "name": "李荣基",
            "tab": "北区居委会书记"
          },
          {
            "level": "村级河长",
            "name": "钟丽珊",
            "tab": "南区居委会书记"
          },
          {
            "level": "村级河长",
            "name": "潘礼全",
            "tab": "东区居委会书记"
          },
          {
            "level": "村级河长",
            "name": "李慰健",
            "tab": "近良居委会书记"
          }
        ],
        "basicDetail": {
          "name": "鹿颈涌",
          "location": "广东省佛山市顺德区大良街区查理街84号",
          "jd": "东经100°",
          "wd": "北纬91°",
          "pq": "大良",
          "ly": "桂畔海",
          "lw": "桂畔海水系",
          "sx": "桂畔海水系",
          "start": "大良",
          "end": "伦教",
          "length": "13.80",
          "width": "27m",
          "deep": "28m",
          "pdeep": "26m"
        },
        "waterDetail": [
          {
            "xzq": "顺德区",
            "szhy": "合益涌",
            "jcsj": "2017.09",
            "szlb": "劣五类",
            "name": "合益涌"
          },
          {
            "xzq": "顺德区",
            "szhy": "合益涌",
            "jcsj": "2017.09",
            "szlb": "劣五类",
            "name": "合益涌"
          }
        ]
      }
    }
  },
  {
    "url": "/gph/app/envir_knowledge/getKnowledgeList",
    "method": "post",
    "response": {
      "code": "0",
      "message": "",
      "body": [
        {
          "title": "怎样评估河流的整治效果？",
          "content": "&nbsp;&nbsp;&nbsp;&nbsp;&nbsp;怎样评估河流的整治效果？对河流状况作出评价，可借鉴医生看病对病人的“望、闻、问、切”等诊断方法，考察河流水体的色泽、气味、透明度；测定水质和底泥的理化指标；考察河流生态系统的结构；分析生态系统的功能及其变化和发展的趋势。严格按照《GB3838-2002 地表水环境质量标准》等国家标准规范来评估治理效果。&nbsp&nbsp&nbsp（二）河水为什么会发黑、发臭？生活污水和一部分工业废水排入水体，其中的有机污染物，如以碳水化合物、蛋白质、脂肪、氨基酸等形式存在的天然有机物质及某些其它可生物降解人工合成的有机物质等进入水体后，使水体中的物质组成发生了变化，破坏了原有的物质平衡状态。在有氧即溶解氧水平较高的情况下，排入水体的有机污染物质，通过物理、化学、物理化学和生物化学反应，而被分离和分解，使水体基本或完全恢复到原来的平衡状态。这称之为水的自我净化能力。"
        },
        {
          "title": "保护环境从我做起",
          "content": "&nbsp&nbsp&nbsp&nbsp&nbsp&nbsp随着经济社会发展和物质消费水平大幅提高，我国生活垃圾产生量迅速增长，环境隐患日益突出，已经成为新型城镇化发展的制约因素。遵循减量化、资源化、无害化的原则，实施生活垃圾分类，可以有效改善城乡环境，促进资源回收利用，加快“两型社会”建设，提高新型城镇化质量和生态文明建设水平。为切实推动生活垃圾分类，根据党中央、国务院有关工作部署，特制定以下方案。"
        },
        {
          "title": "家电辐射的危害",
          "content": "&nbsp&nbsp&nbsp&nbsp&nbsp&nbsp随着经济社会发展和物质消费水平大幅提高，我国生活垃圾产生量迅速增长，环境隐患日益突出，已经成为新型城镇化发展的制约因素。遵循减量化、资源化、无害化的原则，实施生活垃圾分类，可以有效改善城乡环境，促进资源回收利用，加快“两型社会”建设，提高新型城镇化质量和生态文明建设水平。为切实推动生活垃圾分类，根据党中央、国务院有关工作部署，特制定以下方案。"
        },
        {
          "title": "分类处理各种垃圾",
          "content": "&nbsp&nbsp&nbsp&nbsp&nbsp&nbsp随着经济社会发展和物质消费水平大幅提高，我国生活垃圾产生量迅速增长，环境隐患日益突出，已经成为新型城镇化发展的制约因素。遵循减量化、资源化、无害化的原则，实施生活垃圾分类，可以有效改善城乡环境，促进资源回收利用，加快“两型社会”建设，提高新型城镇化质量和生态文明建设水平。为切实推动生活垃圾分类，根据党中央、国务院有关工作部署，特制定以下方案。"
        }
      ]
    }
  },
  {
    "url": "/gph/app/water_knowledge/getKnowledgeList",
    "method": "post",
    "response": {
      "code": "0",
      "message": "",
      "body": [
        {
          "title": "暴雨期间，如何防灾避险？",
          "content": "&nbsp&nbsp&nbsp&nbsp&nbsp&nbsp第一是远离河道。暴雨期间，河流水位极易在短时间内暴涨。原本很浅的河道非常容易成为致命隐患。尤其是住在河道周边危房旧房的居民，要提前组织转移。第三是注意内涝积水处。如果驾车遭遇内涝积水，不能冒险涉水强行通过，否则极易导致"
        },
        {
          "title": "保护环境从我做起",
          "content": "&nbsp&nbsp&nbsp&nbsp&nbsp&nbsp随着经济社会发展和物质消费水平大幅提高，我国生活垃圾产生量迅速增长，环境隐患日益突出，已经成为新型城镇化发展的制约因素。遵循减量化、资源化、无害化的原则，实施生活垃圾分类，可以有效改善城乡环境，促进资源回收利用，加快“两型社会”建设，提高新型城镇化质量和生态文明建设水平。为切实推动生活垃圾分类，根据党中央、国务院有关工作部署，特制定以下方案。"
        },
        {
          "title": "家电辐射的危害",
          "content": "&nbsp&nbsp&nbsp&nbsp&nbsp&nbsp随着经济社会发展和物质消费水平大幅提高，我国生活垃圾产生量迅速增长，环境隐患日益突出，已经成为新型城镇化发展的制约因素。遵循减量化、资源化、无害化的原则，实施生活垃圾分类，可以有效改善城乡环境，促进资源回收利用，加快“两型社会”建设，提高新型城镇化质量和生态文明建设水平。为切实推动生活垃圾分类，根据党中央、国务院有关工作部署，特制定以下方案。"
        },
        {
          "title": "分类处理各种垃圾",
          "content": "&nbsp&nbsp&nbsp&nbsp&nbsp&nbsp随着经济社会发展和物质消费水平大幅提高，我国生活垃圾产生量迅速增长，环境隐患日益突出，已经成为新型城镇化发展的制约因素。遵循减量化、资源化、无害化的原则，实施生活垃圾分类，可以有效改善城乡环境，促进资源回收利用，加快“两型社会”建设，提高新型城镇化质量和生态文明建设水平。为切实推动生活垃圾分类，根据党中央、国务院有关工作部署，特制定以下方案。"
        }
      ]
    }
  },
  {
    "url": "/gph/app/voteActivity/getVoteActivityList",
    "method": "post",
    "response": {
      "code": "0",
      "message": "success",
      "body": [
        {
          "title": "水环境综合整治群众性意向调查问卷",
          "voteTime": "2017-11-21 8:00",
          "content": "为了深入了解公众参与水环境综合整治以及",
          "status": "0"
        },
        {
          "title": "水环境综合整治群众性意向调查问卷",
          "voteTime": "2017-11-21 8:00",
          "content": "为了深入了解公众参与水环境综合整治以及",
          "status": "1"
        },
        {
          "title": "水环境综合整治群众性意向调查问卷",
          "voteTime": "2017-11-21 8:00",
          "content": "为了深入了解公众参与水环境综合整治以及",
          "status": "1"
        },
        {
          "title": "水环境综合整治群众性意向调查问卷",
          "voteTime": "2017-11-21 8:00",
          "content": "为了深入了解公众参与水环境综合整治以及",
          "status": "1"
        },
        {
          "title": "水环境综合整治群众性意向调查问卷",
          "voteTime": "2017-11-21 8:00",
          "content": "为了深入了解公众参与水环境综合整治以及",
          "status": "0"
        },
        {
          "title": "水环境综合整治群众性意向调查问卷",
          "voteTime": "2017-11-21 8:00",
          "content": "为了深入了解公众参与水环境综合整治以及",
          "status": "1"
        }
      ]
    }
  },
  {
    "url": "/gph/app/voteHistory/getVoteHistoryList",
    "method": "post",
    "response": {
      "code": "0",
      "message": "success",
      "body": [
        {
          "title": "水环境综合整治群众性意向调查问卷",
          "issue": "环运局",
          "issueDate": "2017-11-21 8:00",
          "voteStart": "2017-11-21 8:00",
          "voteEnd": "2017-11-21 8:00",
          "status": "0"
        },
        {
          "title": "水环境综合整治群众性意向调查问卷",
          "issue": "环运局",
          "issueDate": "2017-11-21 8:00",
          "voteStart": "2017-11-21 8:00",
          "voteEnd": "2017-11-21 8:00",
          "status": "1"
        },
        {
          "title": "水环境综合整治群众性意向调查问卷",
          "issue": "环运局",
          "issueDate": "2017-11-21 8:00",
          "voteStart": "2017-11-21 8:00",
          "voteEnd": "2017-11-21 8:00",
          "status": "1"
        },
        {
          "title": "水环境综合整治群众性意向调查问卷",
          "issue": "环运局",
          "issueDate": "2017-11-21 8:00",
          "voteStart": "2017-11-21 8:00",
          "voteEnd": "2017-11-21 8:00",
          "status": "0"
        },
        {
          "title": "水环境综合整治群众性意向调查问卷",
          "issue": "环运局",
          "issueDate": "2017-11-21 8:00",
          "voteStart": "2017-11-21 8:00",
          "voteEnd": "2017-11-21 8:00",
          "status": "1"
        },
        {
          "title": "水环境综合整治群众性意向调查问卷",
          "issue": "环运局",
          "issueDate": "2017-11-21 8:00",
          "voteStart": "2017-11-21 8:00",
          "voteEnd": "2017-11-21 8:00",
          "status": "0"
        }
      ]
    }
  },
  {
    "url": "/gph/app/voteActivity/getVoteActivityDetail",
    "method": "post",
    "response": {
      "code": "0",
      "message": "success",
      "body": {
        "title": "水环境综合整治群众性意向调查问卷",
        "issue": "环运局",
        "issueDate": "2017-01-05 8:00",
        "voteStart": "2017-01",
        "voteEnd": "2017-12",
        "content": "为了深入了解公众参与水环境综合整治以及环境信息公开的状况，现通过调查问卷的形式进行调研，希望能得到您的支持，请根据您的实际情况回答下列问题，衷心感谢您的配合！"
      }
    }
  },
  {
    "url": "/gph/app/voteHistory/getVoteHistoryDetail",
    "method": "post",
    "response": {
      "code": "0",
      "message": "success",
      "body": {
        "title": "水环境综合整治群众性意向调查问卷",
        "issue": "环运局",
        "issueDate": "2017-01-05 8:00",
        "voteStart": "2017-01",
        "voteEnd": "2017-12",
        "content": "为了深入了解公众参与水环境综合整治以及环境信息公开的状况，现通过调查问卷的形式进行调研，希望能得到您的支持，请根据您的实际情况回答下列问题，衷心感谢您的配合！"
      }
    }
  },
  {
    "url": "/gph/app/water_knowledge/getKnowledgeDetail",
    "method": "post",
    "response": {
      "code": "0",
      "message": "success",
      "body": {
        "title": "暴雨期间，如何防灾避险？",
        "issueDate": "2017-01-05",
        "issuePerson": "顺德区国土城建和水利局",
        "themeImg": "https://timgsa.baidu.com/timg?image&quality=80&size=b9999_10000&sec=1516008751494&di=ce8bf5c206fcbc29d0f5d66993e26be3&imgtype=0&src=http%3A%2F%2Fimgsrc.baidu.com%2Fimgad%2Fpic%2Fitem%2F09fa513d269759ee0ed0a0e6b9fb43166d22df1f.jpg",
        "html": "&nbsp&nbsp&nbsp&nbsp&nbsp&nbsp暴雨期间，如何防灾避险？<p>&nbsp&nbsp&nbsp&nbsp&nbsp&nbsp第一是远离河道。暴雨期间，河流水位极易在短时间内暴涨。原本很浅的河道非常容易成为致命隐患。尤其是住在河道周边危房旧房的居民，要提前组织转移。<p>&nbsp&nbsp&nbsp&nbsp&nbsp&nbsp第二是远离危险边坡、挡墙等地区。暴雨容易导致边坡、挡墙倒塌，发生伤人事件。<p>&nbsp&nbsp&nbsp&nbsp&nbsp&nbsp第三是注意内涝积水处。如果驾车遭遇内涝积水，不能冒险涉水强行通过，否则极易导致车辆熄火，人员被困。如果遭遇熄火，应第一时间弃车逃生，并报警求助。"
      }
    }
  },
  {
    "url": "/gph/app/envir_knowledge/getKnowledgeDetail",
    "method": "post",
    "response": {
      "code": "0",
      "message": "success",
      "body": {
        "title": "怎样评估河流的整治效果？",
        "issueDate": "2017-01-05",
        "issuePerson": "顺德区环境运输和城市管理局",
        "themeImg": "http://img60.hbzhan.com/3/20161117/636149869201810113328.jpg",
        "html": "&nbsp&nbsp&nbsp（一）怎样评估河流的整治效果？<p>&nbsp&nbsp&nbsp&nbsp对河流状况作出评价，可借鉴医生看病对病人的“望、闻、问、切”等诊断方法，考察河流水体的色泽、气味、透明度；测定水质和底泥的理化指标；考察河流生态系统的结构；分析生态系统的功能及其变化和发展的趋势。严格按照《GB3838-2002 地表水环境质量标准》等国家标准规范来评估治理效果。<p>&nbsp&nbsp&nbsp（二）河水为什么会发黑、发臭？<p>&nbsp&nbsp&nbsp&nbsp&nbsp生活污水和一部分工业废水排入水体，其中的有机污染物，如以碳水化合物、蛋白质、脂肪、氨基酸等形式存在的天然有机物质及某些其它可生物降解人工合成的有机物质等进入水体后，使水体中的物质组成发生了变化，破坏了原有的物质平衡状态。在有氧即溶解氧水平较高的情况下，排入水体的有机污染物质，通过物理、化学、物理化学和生物化学反应，而被分离和分解，使水体基本或完全恢复到原来的平衡状态。这称之为水的自我净化能力。"
      }
    }
  },
  {
    "url": "/gph/app/complaints_query/getComplaintsQueryList",
    "method": "post",
    "response": {
      "code": "0",
      "message": "success",
      "body": [
        {
          "status": 0,
          "title": "河涌垃圾",
          "timeStr": "2017-11-21",
          "content": ""
        },
        {
          "status": 1,
          "title": "红岗涌水臭",
          "timeStr": "2017-11-21",
          "content": ""
        },
        {
          "status": 1,
          "title": "污水处理站废水外流",
          "timeStr": "2017-11-21",
          "content": ""
        },
        {
          "status": 1,
          "title": "管道井盖丢失",
          "timeStr": "2017-11-21",
          "content": ""
        },
        {
          "status": 0,
          "title": "河涌垃圾",
          "timeStr": "2017-11-21",
          "content": ""
        },
        {
          "status": 1,
          "title": "南涌涵闸旁边河道垃圾",
          "timeStr": "2017-11-21",
          "content": ""
        },
        {
          "status": 0,
          "title": "三村水闸垃圾很多",
          "timeStr": "2017-11-21",
          "content": ""
        },
        {
          "status": 0,
          "title": "偷排工业污水",
          "timeStr": "2017-11-21",
          "content": ""
        }
      ]
    }
  }
]
